{
    "clp_clp": 1,
    "clp_cop": 4.45977893,
    "clp_crc": 0.56585825,
    "clp_gtq": 0.0083654273,
    "clp_mxn": 0.020001771,
    "clp_pen": 0.0040905427,
    "clp_usd": 0.0010790659,
    "cop_clp": 0.22422636,
    "cop_cop": 1,
    "cop_crc": 0.12688034,
    "cop_gtq": 0.0018757493,
    "cop_mxn": 0.0044849243,
    "cop_pen": 0.0009172075,
    "cop_usd": 0.00024195501,
    "crc_clp": 1.79346764,
    "crc_cop": 7.95419592,
    "crc_crc": 1,
    "crc_gtq": 0.014861992,
    "crc_mxn": 0.035292754,
    "crc_pen": 0.0073053397,
    "crc_usd": 0.00191699,
    "gtq_clp": 120.67478131,
    "gtq_cop": 535.20388788,
    "gtq_crc": 67.28573115,
    "gtq_gtq": 1,
    "gtq_mxn": 2.37469874,
    "gtq_pen": 0.49154512,
    "gtq_usd": 0.12898607,
    "mxn_clp": 49.99557302,
    "mxn_cop": 222.96920327,
    "mxn_crc": 28.29040727,
    "mxn_gtq": 0.41823433,
    "mxn_mxn": 1,
    "mxn_pen": 0.20450903,
    "mxn_usd": 0.053948517,
    "pen_clp": 244.46634034,
    "pen_cop": 1090.2658344,
    "pen_crc": 138.33329461,
    "pen_gtq": 2.04506541,
    "pen_mxn": 4.88975974,
    "pen_pen": 1,
    "pen_usd": 0.26379529,
    "timestamp": "2024-06-19 06:30:26",
    "usd_clp": 926.72748084,
    "usd_cop": 4132.99969533,
    "usd_crc": 524.39638704,
    "usd_gtq": 7.7524714,
    "usd_mxn": 18.5361908,
    "usd_pen": 3.79081832,
    "usd_usd": 1
}